entrypoints/__init__.py
entrypoints/launch.py
xfuser/__init__.py
xfuser/__version__.py
xfuser/envs.py
xfuser/logger.py
xfuser/parallel.py
xfuser/config/__init__.py
xfuser/config/args.py
xfuser/config/config.py
xfuser/config/diffusers.py
xfuser/core/__init__.py
xfuser/core/cache_manager/__init__.py
xfuser/core/cache_manager/cache_manager.py
xfuser/core/distributed/__init__.py
xfuser/core/distributed/group_coordinator.py
xfuser/core/distributed/parallel_state.py
xfuser/core/distributed/runtime_state.py
xfuser/core/distributed/utils.py
xfuser/core/fast_attention/__init__.py
xfuser/core/fast_attention/attn_layer.py
xfuser/core/fast_attention/fast_attn_state.py
xfuser/core/fast_attention/utils.py
xfuser/core/long_ctx_attention/__init__.py
xfuser/core/long_ctx_attention/hybrid/__init__.py
xfuser/core/long_ctx_attention/hybrid/attn_layer.py
xfuser/core/long_ctx_attention/ring/__init__.py
xfuser/core/long_ctx_attention/ring/ring_flash_attn.py
xfuser/core/utils/__init__.py
xfuser/core/utils/timer.py
xfuser/model_executor/__init__.py
xfuser/model_executor/base_wrapper.py
xfuser/model_executor/cache/__init__.py
xfuser/model_executor/cache/utils.py
xfuser/model_executor/cache/diffusers_adapters/__init__.py
xfuser/model_executor/cache/diffusers_adapters/flux.py
xfuser/model_executor/cache/diffusers_adapters/registry.py
xfuser/model_executor/layers/__init__.py
xfuser/model_executor/layers/attention_processor.py
xfuser/model_executor/layers/base_layer.py
xfuser/model_executor/layers/conv.py
xfuser/model_executor/layers/embeddings.py
xfuser/model_executor/layers/feedforward.py
xfuser/model_executor/layers/register.py
xfuser/model_executor/layers/usp.py
xfuser/model_executor/layers/usp_legacy.py
xfuser/model_executor/models/__init__.py
xfuser/model_executor/models/base_model.py
xfuser/model_executor/models/customized/__init__.py
xfuser/model_executor/models/customized/step_video_t2v/__init__.py
xfuser/model_executor/models/customized/step_video_t2v/attentions.py
xfuser-0.4.5.dist-info/licenses/LICENSE.txt
xfuser-0.4.5.dist-info/METADATA
xfuser-0.4.5.dist-info/WHEEL
xfuser-0.4.5.dist-info/top_level.txt
xfuser-0.4.5.dist-info/RECORD
