Metadata-Version: 2.4
Name: xfuser
Version: 0.4.5
Summary: A Scalable Inference Engine for Diffusion Transformers (DiTs) on Multiple Computing Devices
Home-page: https://github.com/xdit-project/xDiT.
Author: xDiT Team
Author-email: fangjiarui123@gmail.com
Classifier: Programming Language :: Python :: 3
Classifier: Operating System :: OS Independent
Requires-Python: >=3.10
License-File: LICENSE.txt
Requires-Dist: torch>=2.4.1
Requires-Dist: accelerate>=0.33.0
Requires-Dist: transformers>=4.39.1
Requires-Dist: sentencepiece>=0.1.99
Requires-Dist: beautifulsoup4>=4.12.3
Requires-Dist: distvae
Requires-Dist: yunchang>=0.6.0
Requires-Dist: einops
Requires-Dist: diffusers>=0.33.0
Provides-Extra: flash-attn
Requires-Dist: flash-attn>=2.6.0; extra == "flash-attn"
Provides-Extra: optimum-quanto
Requires-Dist: optimum-quanto; extra == "optimum-quanto"
Provides-Extra: flask
Requires-Dist: flask; extra == "flask"
Provides-Extra: ray
Requires-Dist: ray; extra == "ray"
Provides-Extra: opencv-python
Requires-Dist: opencv-python-headless; extra == "opencv-python"
Provides-Extra: test
Requires-Dist: pytest; extra == "test"
Requires-Dist: imageio; extra == "test"
Requires-Dist: imageio-ffmpeg; extra == "test"
Dynamic: author
Dynamic: author-email
Dynamic: classifier
Dynamic: description
Dynamic: description-content-type
Dynamic: home-page
Dynamic: license-file
Dynamic: provides-extra
Dynamic: requires-dist
Dynamic: requires-python
Dynamic: summary
